{
	"configurations" : 
	[
		{
			"directories" : 
			[
				{
					"build" : ".",
					"jsonFile" : "directory-.-Debug-d0094a50bb2071803777.json",
					"minimumCMakeVersion" : 
					{
						"string" : "3.0.0"
					},
					"projectIndex" : 0,
					"source" : ".",
					"targetIndexes" : 
					[
						0,
						1,
						2,
						3,
						4,
						5,
						6
					]
				}
			],
			"name" : "Debug",
			"projects" : 
			[
				{
					"directoryIndexes" : 
					[
						0
					],
					"name" : "first",
					"targetIndexes" : 
					[
						0,
						1,
						2,
						3,
						4,
						5,
						6
					]
				}
			],
			"targets" : 
			[
				{
					"directoryIndex" : 0,
					"id" : "ALL_BUILD::@6890427a1f51a3e7e1df",
					"jsonFile" : "target-ALL_BUILD-Debug-1b89b399bca70e3e0848.json",
					"name" : "ALL_BUILD",
					"projectIndex" : 0
				},
				{
					"directoryIndex" : 0,
					"id" : "Continuous::@6890427a1f51a3e7e1df",
					"jsonFile" : "target-Continuous-Debug-fba2ecca2c4985655259.json",
					"name" : "Continuous",
					"projectIndex" : 0
				},
				{
					"directoryIndex" : 0,
					"id" : "Experimental::@6890427a1f51a3e7e1df",
					"jsonFile" : "target-Experimental-Debug-2fa77297ebc3cfced963.json",
					"name" : "Experimental",
					"projectIndex" : 0
				},
				{
					"directoryIndex" : 0,
					"id" : "Nightly::@6890427a1f51a3e7e1df",
					"jsonFile" : "target-Nightly-Debug-dfa2d008a3052978ce45.json",
					"name" : "Nightly",
					"projectIndex" : 0
				},
				{
					"directoryIndex" : 0,
					"id" : "NightlyMemoryCheck::@6890427a1f51a3e7e1df",
					"jsonFile" : "target-NightlyMemoryCheck-Debug-551207a4ce1da7abdeba.json",
					"name" : "NightlyMemoryCheck",
					"projectIndex" : 0
				},
				{
					"directoryIndex" : 0,
					"id" : "ZERO_CHECK::@6890427a1f51a3e7e1df",
					"jsonFile" : "target-ZERO_CHECK-Debug-6a04edc7040eed6f05f5.json",
					"name" : "ZERO_CHECK",
					"projectIndex" : 0
				},
				{
					"directoryIndex" : 0,
					"id" : "first::@6890427a1f51a3e7e1df",
					"jsonFile" : "target-first-Debug-9ef0561fff936b230143.json",
					"name" : "first",
					"projectIndex" : 0
				}
			]
		},
		{
			"directories" : 
			[
				{
					"build" : ".",
					"jsonFile" : "directory-.-Release-d0094a50bb2071803777.json",
					"minimumCMakeVersion" : 
					{
						"string" : "3.0.0"
					},
					"projectIndex" : 0,
					"source" : ".",
					"targetIndexes" : 
					[
						0,
						1,
						2,
						3,
						4,
						5,
						6
					]
				}
			],
			"name" : "Release",
			"projects" : 
			[
				{
					"directoryIndexes" : 
					[
						0
					],
					"name" : "first",
					"targetIndexes" : 
					[
						0,
						1,
						2,
						3,
						4,
						5,
						6
					]
				}
			],
			"targets" : 
			[
				{
					"directoryIndex" : 0,
					"id" : "ALL_BUILD::@6890427a1f51a3e7e1df",
					"jsonFile" : "target-ALL_BUILD-Release-1b89b399bca70e3e0848.json",
					"name" : "ALL_BUILD",
					"projectIndex" : 0
				},
				{
					"directoryIndex" : 0,
					"id" : "Continuous::@6890427a1f51a3e7e1df",
					"jsonFile" : "target-Continuous-Release-fba2ecca2c4985655259.json",
					"name" : "Continuous",
					"projectIndex" : 0
				},
				{
					"directoryIndex" : 0,
					"id" : "Experimental::@6890427a1f51a3e7e1df",
					"jsonFile" : "target-Experimental-Release-2fa77297ebc3cfced963.json",
					"name" : "Experimental",
					"projectIndex" : 0
				},
				{
					"directoryIndex" : 0,
					"id" : "Nightly::@6890427a1f51a3e7e1df",
					"jsonFile" : "target-Nightly-Release-dfa2d008a3052978ce45.json",
					"name" : "Nightly",
					"projectIndex" : 0
				},
				{
					"directoryIndex" : 0,
					"id" : "NightlyMemoryCheck::@6890427a1f51a3e7e1df",
					"jsonFile" : "target-NightlyMemoryCheck-Release-551207a4ce1da7abdeba.json",
					"name" : "NightlyMemoryCheck",
					"projectIndex" : 0
				},
				{
					"directoryIndex" : 0,
					"id" : "ZERO_CHECK::@6890427a1f51a3e7e1df",
					"jsonFile" : "target-ZERO_CHECK-Release-6a04edc7040eed6f05f5.json",
					"name" : "ZERO_CHECK",
					"projectIndex" : 0
				},
				{
					"directoryIndex" : 0,
					"id" : "first::@6890427a1f51a3e7e1df",
					"jsonFile" : "target-first-Release-243291b96e3e4c5289ee.json",
					"name" : "first",
					"projectIndex" : 0
				}
			]
		},
		{
			"directories" : 
			[
				{
					"build" : ".",
					"jsonFile" : "directory-.-MinSizeRel-d0094a50bb2071803777.json",
					"minimumCMakeVersion" : 
					{
						"string" : "3.0.0"
					},
					"projectIndex" : 0,
					"source" : ".",
					"targetIndexes" : 
					[
						0,
						1,
						2,
						3,
						4,
						5,
						6
					]
				}
			],
			"name" : "MinSizeRel",
			"projects" : 
			[
				{
					"directoryIndexes" : 
					[
						0
					],
					"name" : "first",
					"targetIndexes" : 
					[
						0,
						1,
						2,
						3,
						4,
						5,
						6
					]
				}
			],
			"targets" : 
			[
				{
					"directoryIndex" : 0,
					"id" : "ALL_BUILD::@6890427a1f51a3e7e1df",
					"jsonFile" : "target-ALL_BUILD-MinSizeRel-1b89b399bca70e3e0848.json",
					"name" : "ALL_BUILD",
					"projectIndex" : 0
				},
				{
					"directoryIndex" : 0,
					"id" : "Continuous::@6890427a1f51a3e7e1df",
					"jsonFile" : "target-Continuous-MinSizeRel-fba2ecca2c4985655259.json",
					"name" : "Continuous",
					"projectIndex" : 0
				},
				{
					"directoryIndex" : 0,
					"id" : "Experimental::@6890427a1f51a3e7e1df",
					"jsonFile" : "target-Experimental-MinSizeRel-2fa77297ebc3cfced963.json",
					"name" : "Experimental",
					"projectIndex" : 0
				},
				{
					"directoryIndex" : 0,
					"id" : "Nightly::@6890427a1f51a3e7e1df",
					"jsonFile" : "target-Nightly-MinSizeRel-dfa2d008a3052978ce45.json",
					"name" : "Nightly",
					"projectIndex" : 0
				},
				{
					"directoryIndex" : 0,
					"id" : "NightlyMemoryCheck::@6890427a1f51a3e7e1df",
					"jsonFile" : "target-NightlyMemoryCheck-MinSizeRel-551207a4ce1da7abdeba.json",
					"name" : "NightlyMemoryCheck",
					"projectIndex" : 0
				},
				{
					"directoryIndex" : 0,
					"id" : "ZERO_CHECK::@6890427a1f51a3e7e1df",
					"jsonFile" : "target-ZERO_CHECK-MinSizeRel-6a04edc7040eed6f05f5.json",
					"name" : "ZERO_CHECK",
					"projectIndex" : 0
				},
				{
					"directoryIndex" : 0,
					"id" : "first::@6890427a1f51a3e7e1df",
					"jsonFile" : "target-first-MinSizeRel-023619047ebf729110b2.json",
					"name" : "first",
					"projectIndex" : 0
				}
			]
		},
		{
			"directories" : 
			[
				{
					"build" : ".",
					"jsonFile" : "directory-.-RelWithDebInfo-d0094a50bb2071803777.json",
					"minimumCMakeVersion" : 
					{
						"string" : "3.0.0"
					},
					"projectIndex" : 0,
					"source" : ".",
					"targetIndexes" : 
					[
						0,
						1,
						2,
						3,
						4,
						5,
						6
					]
				}
			],
			"name" : "RelWithDebInfo",
			"projects" : 
			[
				{
					"directoryIndexes" : 
					[
						0
					],
					"name" : "first",
					"targetIndexes" : 
					[
						0,
						1,
						2,
						3,
						4,
						5,
						6
					]
				}
			],
			"targets" : 
			[
				{
					"directoryIndex" : 0,
					"id" : "ALL_BUILD::@6890427a1f51a3e7e1df",
					"jsonFile" : "target-ALL_BUILD-RelWithDebInfo-1b89b399bca70e3e0848.json",
					"name" : "ALL_BUILD",
					"projectIndex" : 0
				},
				{
					"directoryIndex" : 0,
					"id" : "Continuous::@6890427a1f51a3e7e1df",
					"jsonFile" : "target-Continuous-RelWithDebInfo-fba2ecca2c4985655259.json",
					"name" : "Continuous",
					"projectIndex" : 0
				},
				{
					"directoryIndex" : 0,
					"id" : "Experimental::@6890427a1f51a3e7e1df",
					"jsonFile" : "target-Experimental-RelWithDebInfo-2fa77297ebc3cfced963.json",
					"name" : "Experimental",
					"projectIndex" : 0
				},
				{
					"directoryIndex" : 0,
					"id" : "Nightly::@6890427a1f51a3e7e1df",
					"jsonFile" : "target-Nightly-RelWithDebInfo-dfa2d008a3052978ce45.json",
					"name" : "Nightly",
					"projectIndex" : 0
				},
				{
					"directoryIndex" : 0,
					"id" : "NightlyMemoryCheck::@6890427a1f51a3e7e1df",
					"jsonFile" : "target-NightlyMemoryCheck-RelWithDebInfo-551207a4ce1da7abdeba.json",
					"name" : "NightlyMemoryCheck",
					"projectIndex" : 0
				},
				{
					"directoryIndex" : 0,
					"id" : "ZERO_CHECK::@6890427a1f51a3e7e1df",
					"jsonFile" : "target-ZERO_CHECK-RelWithDebInfo-6a04edc7040eed6f05f5.json",
					"name" : "ZERO_CHECK",
					"projectIndex" : 0
				},
				{
					"directoryIndex" : 0,
					"id" : "first::@6890427a1f51a3e7e1df",
					"jsonFile" : "target-first-RelWithDebInfo-4013b799226b98ea3cd7.json",
					"name" : "first",
					"projectIndex" : 0
				}
			]
		}
	],
	"kind" : "codemodel",
	"paths" : 
	{
		"build" : "C:/\u0421\u0442\u043e\u043b/\u0424\u0430\u0439\u043b\u044b/\u0423\u0447\u0451\u0431\u0430/\u0412\u0443\u0437/host/build",
		"source" : "C:/\u0421\u0442\u043e\u043b/\u0424\u0430\u0439\u043b\u044b/\u0423\u0447\u0451\u0431\u0430/\u0412\u0443\u0437/host"
	},
	"version" : 
	{
		"major" : 2,
		"minor" : 6
	}
}
